{
    "ip": "192.168.3.177",
    "port": 8888,
    "portd": 14,
    "sorti1": {
        "s0": "rename",
        "s1": "rename",
        "s2": "SALON1",
        "s3": "rename",
        "s4": "rename",
        "s5": "rename",
        "s6": "rename",
        "s7": "rename"
    },
    "control": {
        "s0": "SALON1",
        "s1": "",
        "s2": "",
        "s3": "",
        "s4": "",
        "s5": "",
        "s6": "",
        "s7": "",
        "s8": "",
        "s9": "",
        "s10": "",
        "s11": "",
        "s12": "",
        "s13": "",
        "s14": "",
        "s15": "",
        "s16": "",
        "s17": "",
        "s18": "",
        "s19": "",
        "s20": "",
        "s21": "",
        "s22": "",
        "s23": "",
        "s24": "",
        "s25": "",
        "s26": "",
        "s27": "",
        "s28": "",
        "s29": "",
        "s30": "",
        "s31": "",
        "s32": "",
        "s33": "",
        "s34": "",
        "s35": "",
        "s36": "",
        "s37": "",
        "s38": "",
        "s39": "",
        "s40": ""
    },
    "watt1": {
        "s0": "",
        "s1": "",
        "s2": "20",
        "s3": "20",
        "s4": "30",
        "s5": "77",
        "s6": "300",
        "s7": "400"
    }
}